<?xml version="1.0" encoding="UTF-8"?><record_update>
    <sys_choice action="INSERT_OR_UPDATE" field="state" table="x_489884_hello_wor_needit" version="3">
        <sys_choice action="INSERT_OR_UPDATE">
            <dependent_value/>
            <element>state</element>
            <hint/>
            <inactive>false</inactive>
            <label>Requested</label>
            <language>en</language>
            <name>x_489884_hello_wor_needit</name>
            <sequence>0</sequence>
            <sys_created_by>admin</sys_created_by>
            <sys_created_on>2020-08-23 11:39:56</sys_created_on>
            <sys_domain>global</sys_domain>
            <sys_domain_path>/</sys_domain_path>
            <sys_id>1caf44b1db325010fcdf8742399619d1</sys_id>
            <sys_mod_count>0</sys_mod_count>
            <sys_updated_by>admin</sys_updated_by>
            <sys_updated_on>2020-08-23 11:39:56</sys_updated_on>
            <value>13</value>
        </sys_choice>
        <sys_choice action="INSERT_OR_UPDATE">
            <dependent_value/>
            <element>state</element>
            <hint/>
            <inactive>false</inactive>
            <label>Awaiting Approval</label>
            <language>en</language>
            <name>x_489884_hello_wor_needit</name>
            <sequence>1</sequence>
            <sys_created_by>admin</sys_created_by>
            <sys_created_on>2020-08-23 11:39:56</sys_created_on>
            <sys_domain>global</sys_domain>
            <sys_domain_path>/</sys_domain_path>
            <sys_id>98af44b1db325010fcdf8742399619d3</sys_id>
            <sys_mod_count>0</sys_mod_count>
            <sys_updated_by>admin</sys_updated_by>
            <sys_updated_on>2020-08-23 11:39:56</sys_updated_on>
            <value>14</value>
        </sys_choice>
        <sys_choice action="INSERT_OR_UPDATE">
            <dependent_value/>
            <element>state</element>
            <hint/>
            <inactive>false</inactive>
            <label>Approved</label>
            <language>en</language>
            <name>x_489884_hello_wor_needit</name>
            <sequence>2</sequence>
            <sys_created_by>admin</sys_created_by>
            <sys_created_on>2020-08-23 11:39:56</sys_created_on>
            <sys_domain>global</sys_domain>
            <sys_domain_path>/</sys_domain_path>
            <sys_id>54af44b1db325010fcdf8742399619d5</sys_id>
            <sys_mod_count>0</sys_mod_count>
            <sys_updated_by>admin</sys_updated_by>
            <sys_updated_on>2020-08-23 11:39:56</sys_updated_on>
            <value>15</value>
        </sys_choice>
        <sys_choice action="INSERT_OR_UPDATE">
            <dependent_value/>
            <element>state</element>
            <hint/>
            <inactive>false</inactive>
            <label>Awaiting Feedback</label>
            <language>en</language>
            <name>x_489884_hello_wor_needit</name>
            <sequence>3</sequence>
            <sys_created_by>admin</sys_created_by>
            <sys_created_on>2020-08-23 11:39:56</sys_created_on>
            <sys_domain>global</sys_domain>
            <sys_domain_path>/</sys_domain_path>
            <sys_id>10af44b1db325010fcdf8742399619d7</sys_id>
            <sys_mod_count>0</sys_mod_count>
            <sys_updated_by>admin</sys_updated_by>
            <sys_updated_on>2020-08-23 11:39:56</sys_updated_on>
            <value>16</value>
        </sys_choice>
        <sys_choice action="INSERT_OR_UPDATE">
            <dependent_value/>
            <element>state</element>
            <hint/>
            <inactive>false</inactive>
            <label>Closed Complete</label>
            <language>en</language>
            <name>x_489884_hello_wor_needit</name>
            <sequence>4</sequence>
            <sys_created_by>admin</sys_created_by>
            <sys_created_on>2020-08-23 11:39:56</sys_created_on>
            <sys_domain>global</sys_domain>
            <sys_domain_path>/</sys_domain_path>
            <sys_id>d8af44b1db325010fcdf8742399619d8</sys_id>
            <sys_mod_count>0</sys_mod_count>
            <sys_updated_by>admin</sys_updated_by>
            <sys_updated_on>2020-08-23 11:39:56</sys_updated_on>
            <value>3</value>
        </sys_choice>
        <sys_choice action="INSERT_OR_UPDATE">
            <dependent_value/>
            <element>state</element>
            <hint/>
            <inactive>false</inactive>
            <label>Withdrawn</label>
            <language>en</language>
            <name>x_489884_hello_wor_needit</name>
            <sequence>5</sequence>
            <sys_created_by>admin</sys_created_by>
            <sys_created_on>2020-08-23 11:39:56</sys_created_on>
            <sys_domain>global</sys_domain>
            <sys_domain_path>/</sys_domain_path>
            <sys_id>54af44b1db325010fcdf8742399619da</sys_id>
            <sys_mod_count>0</sys_mod_count>
            <sys_updated_by>admin</sys_updated_by>
            <sys_updated_on>2020-08-23 11:39:56</sys_updated_on>
            <value>8</value>
        </sys_choice>
        <sys_choice_set action="INSERT_OR_UPDATE">
            <element>state</element>
            <name>x_489884_hello_wor_needit</name>
            <sys_class_name>sys_choice_set</sys_class_name>
            <sys_created_by>admin</sys_created_by>
            <sys_created_on>2020-08-23 11:39:56</sys_created_on>
            <sys_id>54af44b1db325010fcdf8742399619d2</sys_id>
            <sys_mod_count>0</sys_mod_count>
            <sys_name>state</sys_name>
            <sys_package display_value="Hello World" source="x_489884_hello_wor">e38440f1dbfe1010fcdf8742399619ea</sys_package>
            <sys_policy/>
            <sys_scope display_value="Hello World">e38440f1dbfe1010fcdf8742399619ea</sys_scope>
            <sys_update_name>sys_choice_x_489884_hello_wor_needit_state</sys_update_name>
            <sys_updated_by>admin</sys_updated_by>
            <sys_updated_on>2020-08-23 11:39:56</sys_updated_on>
        </sys_choice_set>
    </sys_choice>
</record_update>
